LICENSE
MANIFEST.in
README.md
requirements.txt
setup.cfg
setup.py
footix/__init__.py
footix/cli.py
footix/footix.py
footix.egg-info/PKG-INFO
footix.egg-info/SOURCES.txt
footix.egg-info/dependency_links.txt
footix.egg-info/entry_points.txt
footix.egg-info/not-zip-safe
footix.egg-info/pbr.json
footix.egg-info/requires.txt
footix.egg-info/top_level.txt
tests/__init__.py
tests/test_footix.py