Metadata-Version: 1.1
Name: footix
Version: 2.3.0
Summary: soccer schedule
Home-page: https://github.com/walidsa3d/footix
Author: Walid Saad
Author-email: walid.sa3d@gmail.com
License: MIT
Keywords: football soccer
Platform: UNKNOWN
Classifier: Development Status :: 4 - Beta
Classifier: Environment :: Console
Classifier: Intended Audience :: End Users/Desktop
Classifier: Operating System :: OS Independent
Classifier: Natural Language :: English
Classifier: Programming Language :: Python :: 2
Classifier: Topic :: Utilities
